odoo/addons/carrier_account_environment/README.rst
odoo/addons/carrier_account_environment/__init__.py
odoo/addons/carrier_account_environment/__manifest__.py
odoo/addons/carrier_account_environment/i18n/carrier_account_environment.pot
odoo/addons/carrier_account_environment/i18n/carrier_environment.pot
odoo/addons/carrier_account_environment/i18n/es.po
odoo/addons/carrier_account_environment/i18n/it.po
odoo/addons/carrier_account_environment/i18n/pt_BR.po
odoo/addons/carrier_account_environment/models/__init__.py
odoo/addons/carrier_account_environment/models/carrier_account.py
odoo/addons/carrier_account_environment/readme/CONFIGURE.md
odoo/addons/carrier_account_environment/readme/CONTRIBUTORS.md
odoo/addons/carrier_account_environment/readme/DESCRIPTION.md
odoo/addons/carrier_account_environment/readme/USAGE.md
odoo/addons/carrier_account_environment/static/description/icon.png
odoo/addons/carrier_account_environment/static/description/index.html
odoo/addons/carrier_account_environment/tests/__init__.py
odoo/addons/carrier_account_environment/tests/test_carrier_account_environment.py
odoo_addon_carrier_account_environment-18.0.1.0.0.2.dist-info/METADATA
odoo_addon_carrier_account_environment-18.0.1.0.0.2.dist-info/WHEEL
odoo_addon_carrier_account_environment-18.0.1.0.0.2.dist-info/top_level.txt
odoo_addon_carrier_account_environment-18.0.1.0.0.2.dist-info/RECORD
