Metadata-Version: 2.1
Name: odoo-addon-carrier_account_environment
Version: 18.0.1.0.0.2
Requires-Python: >=3.10
Requires-Dist: odoo-addon-delivery_carrier_account==18.0.*
Requires-Dist: odoo-addon-server_environment==18.0.*
Requires-Dist: odoo==18.0.*
Summary: Configure carriers with server_environment_files
Home-page: https://github.com/OCA/delivery-carrier
License: AGPL-3
Author: Akretion, Camptocamp, Odoo Community Association (OCA)
Author-email: support@odoo-community.org
Classifier: Programming Language :: Python
Classifier: Framework :: Odoo
Classifier: Framework :: Odoo :: 18.0
Classifier: License :: OSI Approved :: GNU Affero General Public License v3
